notion2md/__init__.py
notion2md/__main__.py
notion2md/config.py
notion2md/console/__init__.py
notion2md/console/application.py
notion2md/console/commands/export_block.py
notion2md/console/formatter.py
notion2md/console/ui/__init__.py
notion2md/console/ui/indicator.py
notion2md/convertor/__init__.py
notion2md/convertor/block.py
notion2md/convertor/richtext.py
notion2md/exceptions.py
notion2md/exporter/__init__.py
notion2md/exporter/block.py
notion2md/notion_api.py
notion2md/util.py
notion2md-2.8.4.dist-info/LICENSE
notion2md-2.8.4.dist-info/METADATA
notion2md-2.8.4.dist-info/WHEEL
notion2md-2.8.4.dist-info/entry_points.txt
notion2md-2.8.4.dist-info/RECORD
