Metadata-Version: 2.1
Name: notion2md
Version: 2.8.4
Summary: Notion Markdown Exporter with Python Cli
Home-page: https://github.com/echo724/notion2md.git
License: MIT
Author: echo724
Author-email: eunchan1001@gmail.com
Requires-Python: >=3.7,<4
Classifier: License :: OSI Approved :: MIT License
Classifier: Operating System :: OS Independent
Classifier: Programming Language :: Python :: 3
Classifier: Programming Language :: Python :: 3.7
Classifier: Programming Language :: Python :: 3.8
Classifier: Programming Language :: Python :: 3.9
Classifier: Programming Language :: Python :: 3.10
Classifier: Programming Language :: Python :: 3.11
Classifier: Programming Language :: Python :: 3.12
Requires-Dist: cleo (>=1.0.0a4)
Requires-Dist: notion-client (>=1.0.0)
